soundcloudcharts/__init__.py
soundcloudcharts/api_base.py
soundcloudcharts/client.py
soundcloud_charts_api-1.0.3.dist-info/LICENSE.txt
soundcloud_charts_api-1.0.3.dist-info/METADATA
soundcloud_charts_api-1.0.3.dist-info/WHEEL
soundcloud_charts_api-1.0.3.dist-info/top_level.txt
soundcloud_charts_api-1.0.3.dist-info/RECORD
