Metadata-Version: 2.1
Name: soundcloud-charts-api
Version: 1.0.3
Summary: A python wrapper for the Soundcloud Chart API
Home-page: https://github.com/mpalazzolo/soundcloud-charts-api
Author: Matt Palazzolo
Author-email: mattpalazzolo@gmail.com
License: LICENSE.txt
Platform: UNKNOWN
Requires-Dist: requests (>=2.22.0)
